[
  {
    "id": "M-2026-01",
    "slug": "mexico-vs-south-africa",
    "status": "finished",
    "date": "2026-06-12",
    "time": "",
    "kickoffUtc": "2026-06-11T19:00:00Z",
    "venueId": "azteca",
    "stadium": "Estadio Azteca",
    "city": "Mexico City",
    "country": "Mexico",
    "group": "Group A",
    "stage": "group stage",
    "groupStage": true,
    "home": {
      "id": "T-MEX",
      "name": "Mexico",
      "code": "MEX",
      "nameKo": "멕시코"
    },
    "away": {
      "id": "T-RSA",
      "name": "South Africa",
      "code": "RSA",
      "nameKo": "남아프리카공화국"
    },
    "homeScore": 2,
    "awayScore": 0,
    "penaltyShootout": false,
    "homePenalties": 0,
    "awayPenalties": 0,
    "result": "win",
    "lineups": {
      "home": [],
      "away": []
    },
    "goals": [],
    "bookings": [],
    "subs": [],
    "shootout": []
  },
  {
    "id": "M-2026-02",
    "slug": "south-korea-vs-czech-republic",
    "status": "finished",
    "date": "2026-06-12",
    "time": "",
    "kickoffUtc": "2026-06-12T02:00:00Z",
    "venueId": "akron",
    "stadium": "Estadio Akron",
    "city": "Zapopan",
    "country": "Mexico",
    "group": "Group A",
    "stage": "group stage",
    "groupStage": true,
    "home": {
      "id": "T-KOR",
      "name": "South Korea",
      "code": "KOR",
      "nameKo": "대한민국"
    },
    "away": {
      "id": "T-CZE",
      "name": "Czech Republic",
      "code": "CZE",
      "nameKo": "체코"
    },
    "homeScore": 2,
    "awayScore": 1,
    "penaltyShootout": false,
    "homePenalties": 0,
    "awayPenalties": 0,
    "result": "win",
    "lineups": {
      "home": [],
      "away": []
    },
    "goals": [],
    "bookings": [],
    "subs": [],
    "shootout": []
  },
  {
    "id": "M-2026-03",
    "slug": "czech-republic-vs-south-africa",
    "status": "finished",
    "date": "2026-06-19",
    "time": "",
    "kickoffUtc": "2026-06-18T16:00:00Z",
    "venueId": "atlanta",
    "stadium": "Mercedes-Benz Stadium",
    "city": "Atlanta",
    "country": "United States",
    "group": "Group A",
    "stage": "group stage",
    "groupStage": true,
    "home": {
      "id": "T-CZE",
      "name": "Czech Republic",
      "code": "CZE",
      "nameKo": "체코"
    },
    "away": {
      "id": "T-RSA",
      "name": "South Africa",
      "code": "RSA",
      "nameKo": "남아프리카공화국"
    },
    "homeScore": 1,
    "awayScore": 1,
    "penaltyShootout": false,
    "homePenalties": 0,
    "awayPenalties": 0,
    "result": "draw",
    "lineups": {
      "home": [],
      "away": []
    },
    "goals": [],
    "bookings": [],
    "subs": [],
    "shootout": []
  },
  {
    "id": "M-2026-04",
    "slug": "mexico-vs-south-korea",
    "status": "scheduled",
    "date": "2026-06-19",
    "time": "",
    "kickoffUtc": "2026-06-19T01:00:00Z",
    "venueId": "akron",
    "stadium": "Estadio Akron",
    "city": "Zapopan",
    "country": "Mexico",
    "group": "Group A",
    "stage": "group stage",
    "groupStage": true,
    "home": {
      "id": "T-MEX",
      "name": "Mexico",
      "code": "MEX",
      "nameKo": "멕시코"
    },
    "away": {
      "id": "T-KOR",
      "name": "South Korea",
      "code": "KOR",
      "nameKo": "대한민국"
    },
    "homeScore": 0,
    "awayScore": 0,
    "penaltyShootout": false,
    "homePenalties": 0,
    "awayPenalties": 0,
    "result": "draw",
    "lineups": {
      "home": [],
      "away": []
    },
    "goals": [],
    "bookings": [],
    "subs": [],
    "shootout": []
  },
  {
    "id": "M-2026-05",
    "slug": "czech-republic-vs-mexico",
    "status": "scheduled",
    "date": "2026-06-25",
    "time": "",
    "kickoffUtc": "2026-06-25T01:00:00Z",
    "venueId": "azteca",
    "stadium": "Estadio Azteca",
    "city": "Mexico City",
    "country": "Mexico",
    "group": "Group A",
    "stage": "group stage",
    "groupStage": true,
    "home": {
      "id": "T-CZE",
      "name": "Czech Republic",
      "code": "CZE",
      "nameKo": "체코"
    },
    "away": {
      "id": "T-MEX",
      "name": "Mexico",
      "code": "MEX",
      "nameKo": "멕시코"
    },
    "homeScore": 0,
    "awayScore": 0,
    "penaltyShootout": false,
    "homePenalties": 0,
    "awayPenalties": 0,
    "result": "draw",
    "lineups": {
      "home": [],
      "away": []
    },
    "goals": [],
    "bookings": [],
    "subs": [],
    "shootout": []
  },
  {
    "id": "M-2026-06",
    "slug": "south-africa-vs-south-korea",
    "status": "scheduled",
    "date": "2026-06-25",
    "time": "",
    "kickoffUtc": "2026-06-25T01:00:00Z",
    "venueId": "bbva",
    "stadium": "Estadio BBVA",
    "city": "Guadalupe",
    "country": "Mexico",
    "group": "Group A",
    "stage": "group stage",
    "groupStage": true,
    "home": {
      "id": "T-RSA",
      "name": "South Africa",
      "code": "RSA",
      "nameKo": "남아프리카공화국"
    },
    "away": {
      "id": "T-KOR",
      "name": "South Korea",
      "code": "KOR",
      "nameKo": "대한민국"
    },
    "homeScore": 0,
    "awayScore": 0,
    "penaltyShootout": false,
    "homePenalties": 0,
    "awayPenalties": 0,
    "result": "draw",
    "lineups": {
      "home": [],
      "away": []
    },
    "goals": [],
    "bookings": [],
    "subs": [],
    "shootout": []
  },
  {
    "id": "M-2026-07",
    "slug": "canada-vs-bosnia-and-herzegovina",
    "status": "finished",
    "date": "2026-06-13",
    "time": "",
    "kickoffUtc": "2026-06-12T19:00:00Z",
    "venueId": "toronto",
    "stadium": "BMO Field",
    "city": "Toronto",
    "country": "Canada",
    "group": "Group B",
    "stage": "group stage",
    "groupStage": true,
    "home": {
      "id": "T-CAN",
      "name": "Canada",
      "code": "CAN",
      "nameKo": "캐나다"
    },
    "away": {
      "id": "T-BIH",
      "name": "Bosnia and Herzegovina",
      "code": "BIH",
      "nameKo": "보스니아 헤르체고비나"
    },
    "homeScore": 1,
    "awayScore": 1,
    "penaltyShootout": false,
    "homePenalties": 0,
    "awayPenalties": 0,
    "result": "draw",
    "lineups": {
      "home": [],
      "away": []
    },
    "goals": [],
    "bookings": [],
    "subs": [],
    "shootout": []
  },
  {
    "id": "M-2026-08",
    "slug": "qatar-vs-switzerland",
    "status": "finished",
    "date": "2026-06-14",
    "time": "",
    "kickoffUtc": "2026-06-13T19:00:00Z",
    "venueId": "santaclara",
    "stadium": "Levi's Stadium",
    "city": "Santa Clara",
    "country": "United States",
    "group": "Group B",
    "stage": "group stage",
    "groupStage": true,
    "home": {
      "id": "T-QAT",
      "name": "Qatar",
      "code": "QAT",
      "nameKo": "카타르"
    },
    "away": {
      "id": "T-SUI",
      "name": "Switzerland",
      "code": "SUI",
      "nameKo": "스위스"
    },
    "homeScore": 1,
    "awayScore": 1,
    "penaltyShootout": false,
    "homePenalties": 0,
    "awayPenalties": 0,
    "result": "draw",
    "lineups": {
      "home": [],
      "away": []
    },
    "goals": [],
    "bookings": [],
    "subs": [],
    "shootout": []
  },
  {
    "id": "M-2026-09",
    "slug": "switzerland-vs-bosnia-and-herzegovina",
    "status": "finished",
    "date": "2026-06-19",
    "time": "",
    "kickoffUtc": "2026-06-18T19:00:00Z",
    "venueId": "inglewood",
    "stadium": "SoFi Stadium",
    "city": "Inglewood",
    "country": "United States",
    "group": "Group B",
    "stage": "group stage",
    "groupStage": true,
    "home": {
      "id": "T-SUI",
      "name": "Switzerland",
      "code": "SUI",
      "nameKo": "스위스"
    },
    "away": {
      "id": "T-BIH",
      "name": "Bosnia and Herzegovina",
      "code": "BIH",
      "nameKo": "보스니아 헤르체고비나"
    },
    "homeScore": 4,
    "awayScore": 1,
    "penaltyShootout": false,
    "homePenalties": 0,
    "awayPenalties": 0,
    "result": "win",
    "lineups": {
      "home": [],
      "away": []
    },
    "goals": [],
    "bookings": [],
    "subs": [],
    "shootout": []
  },
  {
    "id": "M-2026-10",
    "slug": "canada-vs-qatar",
    "status": "finished",
    "date": "2026-06-19",
    "time": "",
    "kickoffUtc": "2026-06-18T22:00:00Z",
    "venueId": "vancouver",
    "stadium": "BC Place",
    "city": "Vancouver",
    "country": "Canada",
    "group": "Group B",
    "stage": "group stage",
    "groupStage": true,
    "home": {
      "id": "T-CAN",
      "name": "Canada",
      "code": "CAN",
      "nameKo": "캐나다"
    },
    "away": {
      "id": "T-QAT",
      "name": "Qatar",
      "code": "QAT",
      "nameKo": "카타르"
    },
    "homeScore": 6,
    "awayScore": 0,
    "penaltyShootout": false,
    "homePenalties": 0,
    "awayPenalties": 0,
    "result": "win",
    "lineups": {
      "home": [],
      "away": []
    },
    "goals": [],
    "bookings": [],
    "subs": [],
    "shootout": []
  },
  {
    "id": "M-2026-11",
    "slug": "switzerland-vs-canada",
    "status": "scheduled",
    "date": "2026-06-25",
    "time": "",
    "kickoffUtc": "2026-06-24T19:00:00Z",
    "venueId": "vancouver",
    "stadium": "BC Place",
    "city": "Vancouver",
    "country": "Canada",
    "group": "Group B",
    "stage": "group stage",
    "groupStage": true,
    "home": {
      "id": "T-SUI",
      "name": "Switzerland",
      "code": "SUI",
      "nameKo": "스위스"
    },
    "away": {
      "id": "T-CAN",
      "name": "Canada",
      "code": "CAN",
      "nameKo": "캐나다"
    },
    "homeScore": 0,
    "awayScore": 0,
    "penaltyShootout": false,
    "homePenalties": 0,
    "awayPenalties": 0,
    "result": "draw",
    "lineups": {
      "home": [],
      "away": []
    },
    "goals": [],
    "bookings": [],
    "subs": [],
    "shootout": []
  },
  {
    "id": "M-2026-12",
    "slug": "bosnia-and-herzegovina-vs-qatar",
    "status": "scheduled",
    "date": "2026-06-25",
    "time": "",
    "kickoffUtc": "2026-06-24T19:00:00Z",
    "venueId": "seattle",
    "stadium": "Lumen Field",
    "city": "Seattle",
    "country": "United States",
    "group": "Group B",
    "stage": "group stage",
    "groupStage": true,
    "home": {
      "id": "T-BIH",
      "name": "Bosnia and Herzegovina",
      "code": "BIH",
      "nameKo": "보스니아 헤르체고비나"
    },
    "away": {
      "id": "T-QAT",
      "name": "Qatar",
      "code": "QAT",
      "nameKo": "카타르"
    },
    "homeScore": 0,
    "awayScore": 0,
    "penaltyShootout": false,
    "homePenalties": 0,
    "awayPenalties": 0,
    "result": "draw",
    "lineups": {
      "home": [],
      "away": []
    },
    "goals": [],
    "bookings": [],
    "subs": [],
    "shootout": []
  },
  {
    "id": "M-2026-13",
    "slug": "brazil-vs-morocco",
    "status": "finished",
    "date": "2026-06-14",
    "time": "",
    "kickoffUtc": "2026-06-13T22:00:00Z",
    "venueId": "eastrutherford",
    "stadium": "MetLife Stadium",
    "city": "East Rutherford",
    "country": "United States",
    "group": "Group C",
    "stage": "group stage",
    "groupStage": true,
    "home": {
      "id": "T-BRA",
      "name": "Brazil",
      "code": "BRA",
      "nameKo": "브라질"
    },
    "away": {
      "id": "T-MAR",
      "name": "Morocco",
      "code": "MAR",
      "nameKo": "모로코"
    },
    "homeScore": 1,
    "awayScore": 1,
    "penaltyShootout": false,
    "homePenalties": 0,
    "awayPenalties": 0,
    "result": "draw",
    "lineups": {
      "home": [],
      "away": []
    },
    "goals": [],
    "bookings": [],
    "subs": [],
    "shootout": []
  },
  {
    "id": "M-2026-14",
    "slug": "haiti-vs-scotland",
    "status": "finished",
    "date": "2026-06-14",
    "time": "",
    "kickoffUtc": "2026-06-14T01:00:00Z",
    "venueId": "foxborough",
    "stadium": "Gillette Stadium",
    "city": "Foxborough",
    "country": "United States",
    "group": "Group C",
    "stage": "group stage",
    "groupStage": true,
    "home": {
      "id": "T-HAI",
      "name": "Haiti",
      "code": "HAI",
      "nameKo": "아이티"
    },
    "away": {
      "id": "T-SCO",
      "name": "Scotland",
      "code": "SCO",
      "nameKo": "스코틀랜드"
    },
    "homeScore": 0,
    "awayScore": 1,
    "penaltyShootout": false,
    "homePenalties": 0,
    "awayPenalties": 0,
    "result": "loss",
    "lineups": {
      "home": [],
      "away": []
    },
    "goals": [],
    "bookings": [],
    "subs": [],
    "shootout": []
  },
  {
    "id": "M-2026-15",
    "slug": "scotland-vs-morocco",
    "status": "scheduled",
    "date": "2026-06-20",
    "time": "",
    "kickoffUtc": "2026-06-19T22:00:00Z",
    "venueId": "foxborough",
    "stadium": "Gillette Stadium",
    "city": "Foxborough",
    "country": "United States",
    "group": "Group C",
    "stage": "group stage",
    "groupStage": true,
    "home": {
      "id": "T-SCO",
      "name": "Scotland",
      "code": "SCO",
      "nameKo": "스코틀랜드"
    },
    "away": {
      "id": "T-MAR",
      "name": "Morocco",
      "code": "MAR",
      "nameKo": "모로코"
    },
    "homeScore": 0,
    "awayScore": 0,
    "penaltyShootout": false,
    "homePenalties": 0,
    "awayPenalties": 0,
    "result": "draw",
    "lineups": {
      "home": [],
      "away": []
    },
    "goals": [],
    "bookings": [],
    "subs": [],
    "shootout": []
  },
  {
    "id": "M-2026-16",
    "slug": "brazil-vs-haiti",
    "status": "scheduled",
    "date": "2026-06-20",
    "time": "",
    "kickoffUtc": "2026-06-20T00:30:00Z",
    "venueId": "philadelphia",
    "stadium": "Lincoln Financial Field",
    "city": "Philadelphia",
    "country": "United States",
    "group": "Group C",
    "stage": "group stage",
    "groupStage": true,
    "home": {
      "id": "T-BRA",
      "name": "Brazil",
      "code": "BRA",
      "nameKo": "브라질"
    },
    "away": {
      "id": "T-HAI",
      "name": "Haiti",
      "code": "HAI",
      "nameKo": "아이티"
    },
    "homeScore": 0,
    "awayScore": 0,
    "penaltyShootout": false,
    "homePenalties": 0,
    "awayPenalties": 0,
    "result": "draw",
    "lineups": {
      "home": [],
      "away": []
    },
    "goals": [],
    "bookings": [],
    "subs": [],
    "shootout": []
  },
  {
    "id": "M-2026-17",
    "slug": "scotland-vs-brazil",
    "status": "scheduled",
    "date": "2026-06-25",
    "time": "",
    "kickoffUtc": "2026-06-24T22:00:00Z",
    "venueId": "miami",
    "stadium": "Hard Rock Stadium",
    "city": "Miami Gardens",
    "country": "United States",
    "group": "Group C",
    "stage": "group stage",
    "groupStage": true,
    "home": {
      "id": "T-SCO",
      "name": "Scotland",
      "code": "SCO",
      "nameKo": "스코틀랜드"
    },
    "away": {
      "id": "T-BRA",
      "name": "Brazil",
      "code": "BRA",
      "nameKo": "브라질"
    },
    "homeScore": 0,
    "awayScore": 0,
    "penaltyShootout": false,
    "homePenalties": 0,
    "awayPenalties": 0,
    "result": "draw",
    "lineups": {
      "home": [],
      "away": []
    },
    "goals": [],
    "bookings": [],
    "subs": [],
    "shootout": []
  },
  {
    "id": "M-2026-18",
    "slug": "morocco-vs-haiti",
    "status": "scheduled",
    "date": "2026-06-25",
    "time": "",
    "kickoffUtc": "2026-06-24T22:00:00Z",
    "venueId": "atlanta",
    "stadium": "Mercedes-Benz Stadium",
    "city": "Atlanta",
    "country": "United States",
    "group": "Group C",
    "stage": "group stage",
    "groupStage": true,
    "home": {
      "id": "T-MAR",
      "name": "Morocco",
      "code": "MAR",
      "nameKo": "모로코"
    },
    "away": {
      "id": "T-HAI",
      "name": "Haiti",
      "code": "HAI",
      "nameKo": "아이티"
    },
    "homeScore": 0,
    "awayScore": 0,
    "penaltyShootout": false,
    "homePenalties": 0,
    "awayPenalties": 0,
    "result": "draw",
    "lineups": {
      "home": [],
      "away": []
    },
    "goals": [],
    "bookings": [],
    "subs": [],
    "shootout": []
  },
  {
    "id": "M-2026-19",
    "slug": "united-states-vs-paraguay",
    "status": "finished",
    "date": "2026-06-13",
    "time": "",
    "kickoffUtc": "2026-06-13T01:00:00Z",
    "venueId": "inglewood",
    "stadium": "SoFi Stadium",
    "city": "Inglewood",
    "country": "United States",
    "group": "Group D",
    "stage": "group stage",
    "groupStage": true,
    "home": {
      "id": "T-USA",
      "name": "United States",
      "code": "USA",
      "nameKo": "미국"
    },
    "away": {
      "id": "T-PAR",
      "name": "Paraguay",
      "code": "PAR",
      "nameKo": "파라과이"
    },
    "homeScore": 4,
    "awayScore": 1,
    "penaltyShootout": false,
    "homePenalties": 0,
    "awayPenalties": 0,
    "result": "win",
    "lineups": {
      "home": [],
      "away": []
    },
    "goals": [],
    "bookings": [],
    "subs": [],
    "shootout": []
  },
  {
    "id": "M-2026-20",
    "slug": "australia-vs-turkey",
    "status": "finished",
    "date": "2026-06-14",
    "time": "",
    "kickoffUtc": "2026-06-14T04:00:00Z",
    "venueId": "vancouver",
    "stadium": "BC Place",
    "city": "Vancouver",
    "country": "Canada",
    "group": "Group D",
    "stage": "group stage",
    "groupStage": true,
    "home": {
      "id": "T-AUS",
      "name": "Australia",
      "code": "AUS",
      "nameKo": "호주"
    },
    "away": {
      "id": "T-TUR",
      "name": "Turkey",
      "code": "TUR",
      "nameKo": "터키"
    },
    "homeScore": 2,
    "awayScore": 0,
    "penaltyShootout": false,
    "homePenalties": 0,
    "awayPenalties": 0,
    "result": "win",
    "lineups": {
      "home": [],
      "away": []
    },
    "goals": [],
    "bookings": [],
    "subs": [],
    "shootout": []
  },
  {
    "id": "M-2026-21",
    "slug": "united-states-vs-australia",
    "status": "scheduled",
    "date": "2026-06-20",
    "time": "",
    "kickoffUtc": "2026-06-19T19:00:00Z",
    "venueId": "seattle",
    "stadium": "Lumen Field",
    "city": "Seattle",
    "country": "United States",
    "group": "Group D",
    "stage": "group stage",
    "groupStage": true,
    "home": {
      "id": "T-USA",
      "name": "United States",
      "code": "USA",
      "nameKo": "미국"
    },
    "away": {
      "id": "T-AUS",
      "name": "Australia",
      "code": "AUS",
      "nameKo": "호주"
    },
    "homeScore": 0,
    "awayScore": 0,
    "penaltyShootout": false,
    "homePenalties": 0,
    "awayPenalties": 0,
    "result": "draw",
    "lineups": {
      "home": [],
      "away": []
    },
    "goals": [],
    "bookings": [],
    "subs": [],
    "shootout": []
  },
  {
    "id": "M-2026-22",
    "slug": "turkey-vs-paraguay",
    "status": "scheduled",
    "date": "2026-06-20",
    "time": "",
    "kickoffUtc": "2026-06-20T03:00:00Z",
    "venueId": "santaclara",
    "stadium": "Levi's Stadium",
    "city": "Santa Clara",
    "country": "United States",
    "group": "Group D",
    "stage": "group stage",
    "groupStage": true,
    "home": {
      "id": "T-TUR",
      "name": "Turkey",
      "code": "TUR",
      "nameKo": "터키"
    },
    "away": {
      "id": "T-PAR",
      "name": "Paraguay",
      "code": "PAR",
      "nameKo": "파라과이"
    },
    "homeScore": 0,
    "awayScore": 0,
    "penaltyShootout": false,
    "homePenalties": 0,
    "awayPenalties": 0,
    "result": "draw",
    "lineups": {
      "home": [],
      "away": []
    },
    "goals": [],
    "bookings": [],
    "subs": [],
    "shootout": []
  },
  {
    "id": "M-2026-23",
    "slug": "turkey-vs-united-states",
    "status": "scheduled",
    "date": "2026-06-26",
    "time": "",
    "kickoffUtc": "2026-06-26T02:00:00Z",
    "venueId": "inglewood",
    "stadium": "SoFi Stadium",
    "city": "Inglewood",
    "country": "United States",
    "group": "Group D",
    "stage": "group stage",
    "groupStage": true,
    "home": {
      "id": "T-TUR",
      "name": "Turkey",
      "code": "TUR",
      "nameKo": "터키"
    },
    "away": {
      "id": "T-USA",
      "name": "United States",
      "code": "USA",
      "nameKo": "미국"
    },
    "homeScore": 0,
    "awayScore": 0,
    "penaltyShootout": false,
    "homePenalties": 0,
    "awayPenalties": 0,
    "result": "draw",
    "lineups": {
      "home": [],
      "away": []
    },
    "goals": [],
    "bookings": [],
    "subs": [],
    "shootout": []
  },
  {
    "id": "M-2026-24",
    "slug": "paraguay-vs-australia",
    "status": "scheduled",
    "date": "2026-06-26",
    "time": "",
    "kickoffUtc": "2026-06-26T02:00:00Z",
    "venueId": "santaclara",
    "stadium": "Levi's Stadium",
    "city": "Santa Clara",
    "country": "United States",
    "group": "Group D",
    "stage": "group stage",
    "groupStage": true,
    "home": {
      "id": "T-PAR",
      "name": "Paraguay",
      "code": "PAR",
      "nameKo": "파라과이"
    },
    "away": {
      "id": "T-AUS",
      "name": "Australia",
      "code": "AUS",
      "nameKo": "호주"
    },
    "homeScore": 0,
    "awayScore": 0,
    "penaltyShootout": false,
    "homePenalties": 0,
    "awayPenalties": 0,
    "result": "draw",
    "lineups": {
      "home": [],
      "away": []
    },
    "goals": [],
    "bookings": [],
    "subs": [],
    "shootout": []
  },
  {
    "id": "M-2026-25",
    "slug": "germany-vs-curacao",
    "status": "finished",
    "date": "2026-06-15",
    "time": "",
    "kickoffUtc": "2026-06-14T17:00:00Z",
    "venueId": "houston",
    "stadium": "NRG Stadium",
    "city": "Houston",
    "country": "United States",
    "group": "Group E",
    "stage": "group stage",
    "groupStage": true,
    "home": {
      "id": "T-GER",
      "name": "Germany",
      "code": "GER",
      "nameKo": "독일"
    },
    "away": {
      "id": "T-CUW",
      "name": "Curaçao",
      "code": "CUW",
      "nameKo": "퀴라소"
    },
    "homeScore": 7,
    "awayScore": 1,
    "penaltyShootout": false,
    "homePenalties": 0,
    "awayPenalties": 0,
    "result": "win",
    "lineups": {
      "home": [],
      "away": []
    },
    "goals": [],
    "bookings": [],
    "subs": [],
    "shootout": []
  },
  {
    "id": "M-2026-26",
    "slug": "ivory-coast-vs-ecuador",
    "status": "finished",
    "date": "2026-06-15",
    "time": "",
    "kickoffUtc": "2026-06-14T23:00:00Z",
    "venueId": "philadelphia",
    "stadium": "Lincoln Financial Field",
    "city": "Philadelphia",
    "country": "United States",
    "group": "Group E",
    "stage": "group stage",
    "groupStage": true,
    "home": {
      "id": "T-CIV",
      "name": "Ivory Coast",
      "code": "CIV",
      "nameKo": "코트디부아르"
    },
    "away": {
      "id": "T-ECU",
      "name": "Ecuador",
      "code": "ECU",
      "nameKo": "에콰도르"
    },
    "homeScore": 1,
    "awayScore": 0,
    "penaltyShootout": false,
    "homePenalties": 0,
    "awayPenalties": 0,
    "result": "win",
    "lineups": {
      "home": [],
      "away": []
    },
    "goals": [],
    "bookings": [],
    "subs": [],
    "shootout": []
  },
  {
    "id": "M-2026-27",
    "slug": "germany-vs-ivory-coast",
    "status": "scheduled",
    "date": "2026-06-21",
    "time": "",
    "kickoffUtc": "2026-06-20T20:00:00Z",
    "venueId": "toronto",
    "stadium": "BMO Field",
    "city": "Toronto",
    "country": "Canada",
    "group": "Group E",
    "stage": "group stage",
    "groupStage": true,
    "home": {
      "id": "T-GER",
      "name": "Germany",
      "code": "GER",
      "nameKo": "독일"
    },
    "away": {
      "id": "T-CIV",
      "name": "Ivory Coast",
      "code": "CIV",
      "nameKo": "코트디부아르"
    },
    "homeScore": 0,
    "awayScore": 0,
    "penaltyShootout": false,
    "homePenalties": 0,
    "awayPenalties": 0,
    "result": "draw",
    "lineups": {
      "home": [],
      "away": []
    },
    "goals": [],
    "bookings": [],
    "subs": [],
    "shootout": []
  },
  {
    "id": "M-2026-28",
    "slug": "ecuador-vs-curacao",
    "status": "scheduled",
    "date": "2026-06-21",
    "time": "",
    "kickoffUtc": "2026-06-21T00:00:00Z",
    "venueId": "kansascity",
    "stadium": "Arrowhead Stadium",
    "city": "Kansas City",
    "country": "United States",
    "group": "Group E",
    "stage": "group stage",
    "groupStage": true,
    "home": {
      "id": "T-ECU",
      "name": "Ecuador",
      "code": "ECU",
      "nameKo": "에콰도르"
    },
    "away": {
      "id": "T-CUW",
      "name": "Curaçao",
      "code": "CUW",
      "nameKo": "퀴라소"
    },
    "homeScore": 0,
    "awayScore": 0,
    "penaltyShootout": false,
    "homePenalties": 0,
    "awayPenalties": 0,
    "result": "draw",
    "lineups": {
      "home": [],
      "away": []
    },
    "goals": [],
    "bookings": [],
    "subs": [],
    "shootout": []
  },
  {
    "id": "M-2026-29",
    "slug": "curacao-vs-ivory-coast",
    "status": "scheduled",
    "date": "2026-06-26",
    "time": "",
    "kickoffUtc": "2026-06-25T20:00:00Z",
    "venueId": "philadelphia",
    "stadium": "Lincoln Financial Field",
    "city": "Philadelphia",
    "country": "United States",
    "group": "Group E",
    "stage": "group stage",
    "groupStage": true,
    "home": {
      "id": "T-CUW",
      "name": "Curaçao",
      "code": "CUW",
      "nameKo": "퀴라소"
    },
    "away": {
      "id": "T-CIV",
      "name": "Ivory Coast",
      "code": "CIV",
      "nameKo": "코트디부아르"
    },
    "homeScore": 0,
    "awayScore": 0,
    "penaltyShootout": false,
    "homePenalties": 0,
    "awayPenalties": 0,
    "result": "draw",
    "lineups": {
      "home": [],
      "away": []
    },
    "goals": [],
    "bookings": [],
    "subs": [],
    "shootout": []
  },
  {
    "id": "M-2026-30",
    "slug": "ecuador-vs-germany",
    "status": "scheduled",
    "date": "2026-06-26",
    "time": "",
    "kickoffUtc": "2026-06-25T20:00:00Z",
    "venueId": "eastrutherford",
    "stadium": "MetLife Stadium",
    "city": "East Rutherford",
    "country": "United States",
    "group": "Group E",
    "stage": "group stage",
    "groupStage": true,
    "home": {
      "id": "T-ECU",
      "name": "Ecuador",
      "code": "ECU",
      "nameKo": "에콰도르"
    },
    "away": {
      "id": "T-GER",
      "name": "Germany",
      "code": "GER",
      "nameKo": "독일"
    },
    "homeScore": 0,
    "awayScore": 0,
    "penaltyShootout": false,
    "homePenalties": 0,
    "awayPenalties": 0,
    "result": "draw",
    "lineups": {
      "home": [],
      "away": []
    },
    "goals": [],
    "bookings": [],
    "subs": [],
    "shootout": []
  },
  {
    "id": "M-2026-31",
    "slug": "netherlands-vs-japan",
    "status": "finished",
    "date": "2026-06-15",
    "time": "",
    "kickoffUtc": "2026-06-14T20:00:00Z",
    "venueId": "arlington",
    "stadium": "AT&T Stadium",
    "city": "Arlington",
    "country": "United States",
    "group": "Group F",
    "stage": "group stage",
    "groupStage": true,
    "home": {
      "id": "T-NED",
      "name": "Netherlands",
      "code": "NED",
      "nameKo": "네덜란드"
    },
    "away": {
      "id": "T-JPN",
      "name": "Japan",
      "code": "JPN",
      "nameKo": "일본"
    },
    "homeScore": 2,
    "awayScore": 2,
    "penaltyShootout": false,
    "homePenalties": 0,
    "awayPenalties": 0,
    "result": "draw",
    "lineups": {
      "home": [],
      "away": []
    },
    "goals": [],
    "bookings": [],
    "subs": [],
    "shootout": []
  },
  {
    "id": "M-2026-32",
    "slug": "sweden-vs-tunisia",
    "status": "finished",
    "date": "2026-06-15",
    "time": "",
    "kickoffUtc": "2026-06-15T02:00:00Z",
    "venueId": "bbva",
    "stadium": "Estadio BBVA",
    "city": "Guadalupe",
    "country": "Mexico",
    "group": "Group F",
    "stage": "group stage",
    "groupStage": true,
    "home": {
      "id": "T-SWE",
      "name": "Sweden",
      "code": "SWE",
      "nameKo": "스웨덴"
    },
    "away": {
      "id": "T-TUN",
      "name": "Tunisia",
      "code": "TUN",
      "nameKo": "튀니지"
    },
    "homeScore": 5,
    "awayScore": 1,
    "penaltyShootout": false,
    "homePenalties": 0,
    "awayPenalties": 0,
    "result": "win",
    "lineups": {
      "home": [],
      "away": []
    },
    "goals": [],
    "bookings": [],
    "subs": [],
    "shootout": []
  },
  {
    "id": "M-2026-33",
    "slug": "netherlands-vs-sweden",
    "status": "scheduled",
    "date": "2026-06-21",
    "time": "",
    "kickoffUtc": "2026-06-20T17:00:00Z",
    "venueId": "houston",
    "stadium": "NRG Stadium",
    "city": "Houston",
    "country": "United States",
    "group": "Group F",
    "stage": "group stage",
    "groupStage": true,
    "home": {
      "id": "T-NED",
      "name": "Netherlands",
      "code": "NED",
      "nameKo": "네덜란드"
    },
    "away": {
      "id": "T-SWE",
      "name": "Sweden",
      "code": "SWE",
      "nameKo": "스웨덴"
    },
    "homeScore": 0,
    "awayScore": 0,
    "penaltyShootout": false,
    "homePenalties": 0,
    "awayPenalties": 0,
    "result": "draw",
    "lineups": {
      "home": [],
      "away": []
    },
    "goals": [],
    "bookings": [],
    "subs": [],
    "shootout": []
  },
  {
    "id": "M-2026-34",
    "slug": "tunisia-vs-japan",
    "status": "scheduled",
    "date": "2026-06-21",
    "time": "",
    "kickoffUtc": "2026-06-21T04:00:00Z",
    "venueId": "bbva",
    "stadium": "Estadio BBVA",
    "city": "Guadalupe",
    "country": "Mexico",
    "group": "Group F",
    "stage": "group stage",
    "groupStage": true,
    "home": {
      "id": "T-TUN",
      "name": "Tunisia",
      "code": "TUN",
      "nameKo": "튀니지"
    },
    "away": {
      "id": "T-JPN",
      "name": "Japan",
      "code": "JPN",
      "nameKo": "일본"
    },
    "homeScore": 0,
    "awayScore": 0,
    "penaltyShootout": false,
    "homePenalties": 0,
    "awayPenalties": 0,
    "result": "draw",
    "lineups": {
      "home": [],
      "away": []
    },
    "goals": [],
    "bookings": [],
    "subs": [],
    "shootout": []
  },
  {
    "id": "M-2026-35",
    "slug": "japan-vs-sweden",
    "status": "scheduled",
    "date": "2026-06-26",
    "time": "",
    "kickoffUtc": "2026-06-25T23:00:00Z",
    "venueId": "arlington",
    "stadium": "AT&T Stadium",
    "city": "Arlington",
    "country": "United States",
    "group": "Group F",
    "stage": "group stage",
    "groupStage": true,
    "home": {
      "id": "T-JPN",
      "name": "Japan",
      "code": "JPN",
      "nameKo": "일본"
    },
    "away": {
      "id": "T-SWE",
      "name": "Sweden",
      "code": "SWE",
      "nameKo": "스웨덴"
    },
    "homeScore": 0,
    "awayScore": 0,
    "penaltyShootout": false,
    "homePenalties": 0,
    "awayPenalties": 0,
    "result": "draw",
    "lineups": {
      "home": [],
      "away": []
    },
    "goals": [],
    "bookings": [],
    "subs": [],
    "shootout": []
  },
  {
    "id": "M-2026-36",
    "slug": "tunisia-vs-netherlands",
    "status": "scheduled",
    "date": "2026-06-26",
    "time": "",
    "kickoffUtc": "2026-06-25T23:00:00Z",
    "venueId": "kansascity",
    "stadium": "Arrowhead Stadium",
    "city": "Kansas City",
    "country": "United States",
    "group": "Group F",
    "stage": "group stage",
    "groupStage": true,
    "home": {
      "id": "T-TUN",
      "name": "Tunisia",
      "code": "TUN",
      "nameKo": "튀니지"
    },
    "away": {
      "id": "T-NED",
      "name": "Netherlands",
      "code": "NED",
      "nameKo": "네덜란드"
    },
    "homeScore": 0,
    "awayScore": 0,
    "penaltyShootout": false,
    "homePenalties": 0,
    "awayPenalties": 0,
    "result": "draw",
    "lineups": {
      "home": [],
      "away": []
    },
    "goals": [],
    "bookings": [],
    "subs": [],
    "shootout": []
  },
  {
    "id": "M-2026-37",
    "slug": "belgium-vs-egypt",
    "status": "finished",
    "date": "2026-06-16",
    "time": "",
    "kickoffUtc": "2026-06-15T19:00:00Z",
    "venueId": "seattle",
    "stadium": "Lumen Field",
    "city": "Seattle",
    "country": "United States",
    "group": "Group G",
    "stage": "group stage",
    "groupStage": true,
    "home": {
      "id": "T-BEL",
      "name": "Belgium",
      "code": "BEL",
      "nameKo": "벨기에"
    },
    "away": {
      "id": "T-EGY",
      "name": "Egypt",
      "code": "EGY",
      "nameKo": "이집트"
    },
    "homeScore": 1,
    "awayScore": 1,
    "penaltyShootout": false,
    "homePenalties": 0,
    "awayPenalties": 0,
    "result": "draw",
    "lineups": {
      "home": [],
      "away": []
    },
    "goals": [],
    "bookings": [],
    "subs": [],
    "shootout": []
  },
  {
    "id": "M-2026-38",
    "slug": "iran-vs-new-zealand",
    "status": "finished",
    "date": "2026-06-16",
    "time": "",
    "kickoffUtc": "2026-06-16T01:00:00Z",
    "venueId": "inglewood",
    "stadium": "SoFi Stadium",
    "city": "Inglewood",
    "country": "United States",
    "group": "Group G",
    "stage": "group stage",
    "groupStage": true,
    "home": {
      "id": "T-IRN",
      "name": "Iran",
      "code": "IRN",
      "nameKo": "이란"
    },
    "away": {
      "id": "T-NZL",
      "name": "New Zealand",
      "code": "NZL",
      "nameKo": "뉴질랜드"
    },
    "homeScore": 2,
    "awayScore": 2,
    "penaltyShootout": false,
    "homePenalties": 0,
    "awayPenalties": 0,
    "result": "draw",
    "lineups": {
      "home": [],
      "away": []
    },
    "goals": [],
    "bookings": [],
    "subs": [],
    "shootout": []
  },
  {
    "id": "M-2026-39",
    "slug": "belgium-vs-iran",
    "status": "scheduled",
    "date": "2026-06-22",
    "time": "",
    "kickoffUtc": "2026-06-21T19:00:00Z",
    "venueId": "inglewood",
    "stadium": "SoFi Stadium",
    "city": "Inglewood",
    "country": "United States",
    "group": "Group G",
    "stage": "group stage",
    "groupStage": true,
    "home": {
      "id": "T-BEL",
      "name": "Belgium",
      "code": "BEL",
      "nameKo": "벨기에"
    },
    "away": {
      "id": "T-IRN",
      "name": "Iran",
      "code": "IRN",
      "nameKo": "이란"
    },
    "homeScore": 0,
    "awayScore": 0,
    "penaltyShootout": false,
    "homePenalties": 0,
    "awayPenalties": 0,
    "result": "draw",
    "lineups": {
      "home": [],
      "away": []
    },
    "goals": [],
    "bookings": [],
    "subs": [],
    "shootout": []
  },
  {
    "id": "M-2026-40",
    "slug": "new-zealand-vs-egypt",
    "status": "scheduled",
    "date": "2026-06-22",
    "time": "",
    "kickoffUtc": "2026-06-22T01:00:00Z",
    "venueId": "vancouver",
    "stadium": "BC Place",
    "city": "Vancouver",
    "country": "Canada",
    "group": "Group G",
    "stage": "group stage",
    "groupStage": true,
    "home": {
      "id": "T-NZL",
      "name": "New Zealand",
      "code": "NZL",
      "nameKo": "뉴질랜드"
    },
    "away": {
      "id": "T-EGY",
      "name": "Egypt",
      "code": "EGY",
      "nameKo": "이집트"
    },
    "homeScore": 0,
    "awayScore": 0,
    "penaltyShootout": false,
    "homePenalties": 0,
    "awayPenalties": 0,
    "result": "draw",
    "lineups": {
      "home": [],
      "away": []
    },
    "goals": [],
    "bookings": [],
    "subs": [],
    "shootout": []
  },
  {
    "id": "M-2026-41",
    "slug": "egypt-vs-iran",
    "status": "scheduled",
    "date": "2026-06-27",
    "time": "",
    "kickoffUtc": "2026-06-27T03:00:00Z",
    "venueId": "seattle",
    "stadium": "Lumen Field",
    "city": "Seattle",
    "country": "United States",
    "group": "Group G",
    "stage": "group stage",
    "groupStage": true,
    "home": {
      "id": "T-EGY",
      "name": "Egypt",
      "code": "EGY",
      "nameKo": "이집트"
    },
    "away": {
      "id": "T-IRN",
      "name": "Iran",
      "code": "IRN",
      "nameKo": "이란"
    },
    "homeScore": 0,
    "awayScore": 0,
    "penaltyShootout": false,
    "homePenalties": 0,
    "awayPenalties": 0,
    "result": "draw",
    "lineups": {
      "home": [],
      "away": []
    },
    "goals": [],
    "bookings": [],
    "subs": [],
    "shootout": []
  },
  {
    "id": "M-2026-42",
    "slug": "new-zealand-vs-belgium",
    "status": "scheduled",
    "date": "2026-06-27",
    "time": "",
    "kickoffUtc": "2026-06-27T03:00:00Z",
    "venueId": "vancouver",
    "stadium": "BC Place",
    "city": "Vancouver",
    "country": "Canada",
    "group": "Group G",
    "stage": "group stage",
    "groupStage": true,
    "home": {
      "id": "T-NZL",
      "name": "New Zealand",
      "code": "NZL",
      "nameKo": "뉴질랜드"
    },
    "away": {
      "id": "T-BEL",
      "name": "Belgium",
      "code": "BEL",
      "nameKo": "벨기에"
    },
    "homeScore": 0,
    "awayScore": 0,
    "penaltyShootout": false,
    "homePenalties": 0,
    "awayPenalties": 0,
    "result": "draw",
    "lineups": {
      "home": [],
      "away": []
    },
    "goals": [],
    "bookings": [],
    "subs": [],
    "shootout": []
  },
  {
    "id": "M-2026-43",
    "slug": "spain-vs-cape-verde",
    "status": "finished",
    "date": "2026-06-16",
    "time": "",
    "kickoffUtc": "2026-06-15T16:00:00Z",
    "venueId": "atlanta",
    "stadium": "Mercedes-Benz Stadium",
    "city": "Atlanta",
    "country": "United States",
    "group": "Group H",
    "stage": "group stage",
    "groupStage": true,
    "home": {
      "id": "T-ESP",
      "name": "Spain",
      "code": "ESP",
      "nameKo": "스페인"
    },
    "away": {
      "id": "T-CPV",
      "name": "Cape Verde",
      "code": "CPV",
      "nameKo": "카보베르데"
    },
    "homeScore": 0,
    "awayScore": 0,
    "penaltyShootout": false,
    "homePenalties": 0,
    "awayPenalties": 0,
    "result": "draw",
    "lineups": {
      "home": [],
      "away": []
    },
    "goals": [],
    "bookings": [],
    "subs": [],
    "shootout": []
  },
  {
    "id": "M-2026-44",
    "slug": "saudi-arabia-vs-uruguay",
    "status": "finished",
    "date": "2026-06-16",
    "time": "",
    "kickoffUtc": "2026-06-15T22:00:00Z",
    "venueId": "miami",
    "stadium": "Hard Rock Stadium",
    "city": "Miami Gardens",
    "country": "United States",
    "group": "Group H",
    "stage": "group stage",
    "groupStage": true,
    "home": {
      "id": "T-KSA",
      "name": "Saudi Arabia",
      "code": "KSA",
      "nameKo": "사우디아라비아"
    },
    "away": {
      "id": "T-URU",
      "name": "Uruguay",
      "code": "URU",
      "nameKo": "우루과이"
    },
    "homeScore": 1,
    "awayScore": 1,
    "penaltyShootout": false,
    "homePenalties": 0,
    "awayPenalties": 0,
    "result": "draw",
    "lineups": {
      "home": [],
      "away": []
    },
    "goals": [],
    "bookings": [],
    "subs": [],
    "shootout": []
  },
  {
    "id": "M-2026-45",
    "slug": "spain-vs-saudi-arabia",
    "status": "scheduled",
    "date": "2026-06-22",
    "time": "",
    "kickoffUtc": "2026-06-21T16:00:00Z",
    "venueId": "atlanta",
    "stadium": "Mercedes-Benz Stadium",
    "city": "Atlanta",
    "country": "United States",
    "group": "Group H",
    "stage": "group stage",
    "groupStage": true,
    "home": {
      "id": "T-ESP",
      "name": "Spain",
      "code": "ESP",
      "nameKo": "스페인"
    },
    "away": {
      "id": "T-KSA",
      "name": "Saudi Arabia",
      "code": "KSA",
      "nameKo": "사우디아라비아"
    },
    "homeScore": 0,
    "awayScore": 0,
    "penaltyShootout": false,
    "homePenalties": 0,
    "awayPenalties": 0,
    "result": "draw",
    "lineups": {
      "home": [],
      "away": []
    },
    "goals": [],
    "bookings": [],
    "subs": [],
    "shootout": []
  },
  {
    "id": "M-2026-46",
    "slug": "uruguay-vs-cape-verde",
    "status": "scheduled",
    "date": "2026-06-22",
    "time": "",
    "kickoffUtc": "2026-06-21T22:00:00Z",
    "venueId": "miami",
    "stadium": "Hard Rock Stadium",
    "city": "Miami Gardens",
    "country": "United States",
    "group": "Group H",
    "stage": "group stage",
    "groupStage": true,
    "home": {
      "id": "T-URU",
      "name": "Uruguay",
      "code": "URU",
      "nameKo": "우루과이"
    },
    "away": {
      "id": "T-CPV",
      "name": "Cape Verde",
      "code": "CPV",
      "nameKo": "카보베르데"
    },
    "homeScore": 0,
    "awayScore": 0,
    "penaltyShootout": false,
    "homePenalties": 0,
    "awayPenalties": 0,
    "result": "draw",
    "lineups": {
      "home": [],
      "away": []
    },
    "goals": [],
    "bookings": [],
    "subs": [],
    "shootout": []
  },
  {
    "id": "M-2026-47",
    "slug": "cape-verde-vs-saudi-arabia",
    "status": "scheduled",
    "date": "2026-06-27",
    "time": "",
    "kickoffUtc": "2026-06-27T00:00:00Z",
    "venueId": "houston",
    "stadium": "NRG Stadium",
    "city": "Houston",
    "country": "United States",
    "group": "Group H",
    "stage": "group stage",
    "groupStage": true,
    "home": {
      "id": "T-CPV",
      "name": "Cape Verde",
      "code": "CPV",
      "nameKo": "카보베르데"
    },
    "away": {
      "id": "T-KSA",
      "name": "Saudi Arabia",
      "code": "KSA",
      "nameKo": "사우디아라비아"
    },
    "homeScore": 0,
    "awayScore": 0,
    "penaltyShootout": false,
    "homePenalties": 0,
    "awayPenalties": 0,
    "result": "draw",
    "lineups": {
      "home": [],
      "away": []
    },
    "goals": [],
    "bookings": [],
    "subs": [],
    "shootout": []
  },
  {
    "id": "M-2026-48",
    "slug": "uruguay-vs-spain",
    "status": "scheduled",
    "date": "2026-06-27",
    "time": "",
    "kickoffUtc": "2026-06-27T00:00:00Z",
    "venueId": "akron",
    "stadium": "Estadio Akron",
    "city": "Zapopan",
    "country": "Mexico",
    "group": "Group H",
    "stage": "group stage",
    "groupStage": true,
    "home": {
      "id": "T-URU",
      "name": "Uruguay",
      "code": "URU",
      "nameKo": "우루과이"
    },
    "away": {
      "id": "T-ESP",
      "name": "Spain",
      "code": "ESP",
      "nameKo": "스페인"
    },
    "homeScore": 0,
    "awayScore": 0,
    "penaltyShootout": false,
    "homePenalties": 0,
    "awayPenalties": 0,
    "result": "draw",
    "lineups": {
      "home": [],
      "away": []
    },
    "goals": [],
    "bookings": [],
    "subs": [],
    "shootout": []
  },
  {
    "id": "M-2026-49",
    "slug": "france-vs-senegal",
    "status": "finished",
    "date": "2026-06-17",
    "time": "",
    "kickoffUtc": "2026-06-16T19:00:00Z",
    "venueId": "eastrutherford",
    "stadium": "MetLife Stadium",
    "city": "East Rutherford",
    "country": "United States",
    "group": "Group I",
    "stage": "group stage",
    "groupStage": true,
    "home": {
      "id": "T-FRA",
      "name": "France",
      "code": "FRA",
      "nameKo": "프랑스"
    },
    "away": {
      "id": "T-SEN",
      "name": "Senegal",
      "code": "SEN",
      "nameKo": "세네갈"
    },
    "homeScore": 3,
    "awayScore": 1,
    "penaltyShootout": false,
    "homePenalties": 0,
    "awayPenalties": 0,
    "result": "win",
    "lineups": {
      "home": [],
      "away": []
    },
    "goals": [],
    "bookings": [],
    "subs": [],
    "shootout": []
  },
  {
    "id": "M-2026-50",
    "slug": "iraq-vs-norway",
    "status": "finished",
    "date": "2026-06-17",
    "time": "",
    "kickoffUtc": "2026-06-16T22:00:00Z",
    "venueId": "foxborough",
    "stadium": "Gillette Stadium",
    "city": "Foxborough",
    "country": "United States",
    "group": "Group I",
    "stage": "group stage",
    "groupStage": true,
    "home": {
      "id": "T-IRQ",
      "name": "Iraq",
      "code": "IRQ",
      "nameKo": "이라크"
    },
    "away": {
      "id": "T-NOR",
      "name": "Norway",
      "code": "NOR",
      "nameKo": "노르웨이"
    },
    "homeScore": 1,
    "awayScore": 4,
    "penaltyShootout": false,
    "homePenalties": 0,
    "awayPenalties": 0,
    "result": "loss",
    "lineups": {
      "home": [],
      "away": []
    },
    "goals": [],
    "bookings": [],
    "subs": [],
    "shootout": []
  },
  {
    "id": "M-2026-51",
    "slug": "france-vs-iraq",
    "status": "scheduled",
    "date": "2026-06-23",
    "time": "",
    "kickoffUtc": "2026-06-22T21:00:00Z",
    "venueId": "philadelphia",
    "stadium": "Lincoln Financial Field",
    "city": "Philadelphia",
    "country": "United States",
    "group": "Group I",
    "stage": "group stage",
    "groupStage": true,
    "home": {
      "id": "T-FRA",
      "name": "France",
      "code": "FRA",
      "nameKo": "프랑스"
    },
    "away": {
      "id": "T-IRQ",
      "name": "Iraq",
      "code": "IRQ",
      "nameKo": "이라크"
    },
    "homeScore": 0,
    "awayScore": 0,
    "penaltyShootout": false,
    "homePenalties": 0,
    "awayPenalties": 0,
    "result": "draw",
    "lineups": {
      "home": [],
      "away": []
    },
    "goals": [],
    "bookings": [],
    "subs": [],
    "shootout": []
  },
  {
    "id": "M-2026-52",
    "slug": "norway-vs-senegal",
    "status": "scheduled",
    "date": "2026-06-23",
    "time": "",
    "kickoffUtc": "2026-06-23T00:00:00Z",
    "venueId": "eastrutherford",
    "stadium": "MetLife Stadium",
    "city": "East Rutherford",
    "country": "United States",
    "group": "Group I",
    "stage": "group stage",
    "groupStage": true,
    "home": {
      "id": "T-NOR",
      "name": "Norway",
      "code": "NOR",
      "nameKo": "노르웨이"
    },
    "away": {
      "id": "T-SEN",
      "name": "Senegal",
      "code": "SEN",
      "nameKo": "세네갈"
    },
    "homeScore": 0,
    "awayScore": 0,
    "penaltyShootout": false,
    "homePenalties": 0,
    "awayPenalties": 0,
    "result": "draw",
    "lineups": {
      "home": [],
      "away": []
    },
    "goals": [],
    "bookings": [],
    "subs": [],
    "shootout": []
  },
  {
    "id": "M-2026-53",
    "slug": "norway-vs-france",
    "status": "scheduled",
    "date": "2026-06-27",
    "time": "",
    "kickoffUtc": "2026-06-26T19:00:00Z",
    "venueId": "foxborough",
    "stadium": "Gillette Stadium",
    "city": "Foxborough",
    "country": "United States",
    "group": "Group I",
    "stage": "group stage",
    "groupStage": true,
    "home": {
      "id": "T-NOR",
      "name": "Norway",
      "code": "NOR",
      "nameKo": "노르웨이"
    },
    "away": {
      "id": "T-FRA",
      "name": "France",
      "code": "FRA",
      "nameKo": "프랑스"
    },
    "homeScore": 0,
    "awayScore": 0,
    "penaltyShootout": false,
    "homePenalties": 0,
    "awayPenalties": 0,
    "result": "draw",
    "lineups": {
      "home": [],
      "away": []
    },
    "goals": [],
    "bookings": [],
    "subs": [],
    "shootout": []
  },
  {
    "id": "M-2026-54",
    "slug": "senegal-vs-iraq",
    "status": "scheduled",
    "date": "2026-06-27",
    "time": "",
    "kickoffUtc": "2026-06-26T19:00:00Z",
    "venueId": "toronto",
    "stadium": "BMO Field",
    "city": "Toronto",
    "country": "Canada",
    "group": "Group I",
    "stage": "group stage",
    "groupStage": true,
    "home": {
      "id": "T-SEN",
      "name": "Senegal",
      "code": "SEN",
      "nameKo": "세네갈"
    },
    "away": {
      "id": "T-IRQ",
      "name": "Iraq",
      "code": "IRQ",
      "nameKo": "이라크"
    },
    "homeScore": 0,
    "awayScore": 0,
    "penaltyShootout": false,
    "homePenalties": 0,
    "awayPenalties": 0,
    "result": "draw",
    "lineups": {
      "home": [],
      "away": []
    },
    "goals": [],
    "bookings": [],
    "subs": [],
    "shootout": []
  },
  {
    "id": "M-2026-55",
    "slug": "argentina-vs-algeria",
    "status": "finished",
    "date": "2026-06-17",
    "time": "",
    "kickoffUtc": "2026-06-17T01:00:00Z",
    "venueId": "kansascity",
    "stadium": "Arrowhead Stadium",
    "city": "Kansas City",
    "country": "United States",
    "group": "Group J",
    "stage": "group stage",
    "groupStage": true,
    "home": {
      "id": "T-ARG",
      "name": "Argentina",
      "code": "ARG",
      "nameKo": "아르헨티나"
    },
    "away": {
      "id": "T-ALG",
      "name": "Algeria",
      "code": "ALG",
      "nameKo": "알제리"
    },
    "homeScore": 3,
    "awayScore": 0,
    "penaltyShootout": false,
    "homePenalties": 0,
    "awayPenalties": 0,
    "result": "win",
    "lineups": {
      "home": [],
      "away": []
    },
    "goals": [],
    "bookings": [],
    "subs": [],
    "shootout": []
  },
  {
    "id": "M-2026-56",
    "slug": "austria-vs-jordan",
    "status": "finished",
    "date": "2026-06-17",
    "time": "",
    "kickoffUtc": "2026-06-17T04:00:00Z",
    "venueId": "santaclara",
    "stadium": "Levi's Stadium",
    "city": "Santa Clara",
    "country": "United States",
    "group": "Group J",
    "stage": "group stage",
    "groupStage": true,
    "home": {
      "id": "T-AUT",
      "name": "Austria",
      "code": "AUT",
      "nameKo": "오스트리아"
    },
    "away": {
      "id": "T-JOR",
      "name": "Jordan",
      "code": "JOR",
      "nameKo": "요르단"
    },
    "homeScore": 3,
    "awayScore": 1,
    "penaltyShootout": false,
    "homePenalties": 0,
    "awayPenalties": 0,
    "result": "win",
    "lineups": {
      "home": [],
      "away": []
    },
    "goals": [],
    "bookings": [],
    "subs": [],
    "shootout": []
  },
  {
    "id": "M-2026-57",
    "slug": "argentina-vs-austria",
    "status": "scheduled",
    "date": "2026-06-23",
    "time": "",
    "kickoffUtc": "2026-06-22T17:00:00Z",
    "venueId": "arlington",
    "stadium": "AT&T Stadium",
    "city": "Arlington",
    "country": "United States",
    "group": "Group J",
    "stage": "group stage",
    "groupStage": true,
    "home": {
      "id": "T-ARG",
      "name": "Argentina",
      "code": "ARG",
      "nameKo": "아르헨티나"
    },
    "away": {
      "id": "T-AUT",
      "name": "Austria",
      "code": "AUT",
      "nameKo": "오스트리아"
    },
    "homeScore": 0,
    "awayScore": 0,
    "penaltyShootout": false,
    "homePenalties": 0,
    "awayPenalties": 0,
    "result": "draw",
    "lineups": {
      "home": [],
      "away": []
    },
    "goals": [],
    "bookings": [],
    "subs": [],
    "shootout": []
  },
  {
    "id": "M-2026-58",
    "slug": "jordan-vs-algeria",
    "status": "scheduled",
    "date": "2026-06-23",
    "time": "",
    "kickoffUtc": "2026-06-23T03:00:00Z",
    "venueId": "santaclara",
    "stadium": "Levi's Stadium",
    "city": "Santa Clara",
    "country": "United States",
    "group": "Group J",
    "stage": "group stage",
    "groupStage": true,
    "home": {
      "id": "T-JOR",
      "name": "Jordan",
      "code": "JOR",
      "nameKo": "요르단"
    },
    "away": {
      "id": "T-ALG",
      "name": "Algeria",
      "code": "ALG",
      "nameKo": "알제리"
    },
    "homeScore": 0,
    "awayScore": 0,
    "penaltyShootout": false,
    "homePenalties": 0,
    "awayPenalties": 0,
    "result": "draw",
    "lineups": {
      "home": [],
      "away": []
    },
    "goals": [],
    "bookings": [],
    "subs": [],
    "shootout": []
  },
  {
    "id": "M-2026-59",
    "slug": "algeria-vs-austria",
    "status": "scheduled",
    "date": "2026-06-28",
    "time": "",
    "kickoffUtc": "2026-06-28T02:00:00Z",
    "venueId": "kansascity",
    "stadium": "Arrowhead Stadium",
    "city": "Kansas City",
    "country": "United States",
    "group": "Group J",
    "stage": "group stage",
    "groupStage": true,
    "home": {
      "id": "T-ALG",
      "name": "Algeria",
      "code": "ALG",
      "nameKo": "알제리"
    },
    "away": {
      "id": "T-AUT",
      "name": "Austria",
      "code": "AUT",
      "nameKo": "오스트리아"
    },
    "homeScore": 0,
    "awayScore": 0,
    "penaltyShootout": false,
    "homePenalties": 0,
    "awayPenalties": 0,
    "result": "draw",
    "lineups": {
      "home": [],
      "away": []
    },
    "goals": [],
    "bookings": [],
    "subs": [],
    "shootout": []
  },
  {
    "id": "M-2026-60",
    "slug": "jordan-vs-argentina",
    "status": "scheduled",
    "date": "2026-06-28",
    "time": "",
    "kickoffUtc": "2026-06-28T02:00:00Z",
    "venueId": "arlington",
    "stadium": "AT&T Stadium",
    "city": "Arlington",
    "country": "United States",
    "group": "Group J",
    "stage": "group stage",
    "groupStage": true,
    "home": {
      "id": "T-JOR",
      "name": "Jordan",
      "code": "JOR",
      "nameKo": "요르단"
    },
    "away": {
      "id": "T-ARG",
      "name": "Argentina",
      "code": "ARG",
      "nameKo": "아르헨티나"
    },
    "homeScore": 0,
    "awayScore": 0,
    "penaltyShootout": false,
    "homePenalties": 0,
    "awayPenalties": 0,
    "result": "draw",
    "lineups": {
      "home": [],
      "away": []
    },
    "goals": [],
    "bookings": [],
    "subs": [],
    "shootout": []
  },
  {
    "id": "M-2026-61",
    "slug": "portugal-vs-dr-congo",
    "status": "finished",
    "date": "2026-06-18",
    "time": "",
    "kickoffUtc": "2026-06-17T17:00:00Z",
    "venueId": "houston",
    "stadium": "NRG Stadium",
    "city": "Houston",
    "country": "United States",
    "group": "Group K",
    "stage": "group stage",
    "groupStage": true,
    "home": {
      "id": "T-POR",
      "name": "Portugal",
      "code": "POR",
      "nameKo": "포르투갈"
    },
    "away": {
      "id": "T-COD",
      "name": "DR Congo",
      "code": "COD",
      "nameKo": "콩고민주공화국"
    },
    "homeScore": 1,
    "awayScore": 1,
    "penaltyShootout": false,
    "homePenalties": 0,
    "awayPenalties": 0,
    "result": "draw",
    "lineups": {
      "home": [],
      "away": []
    },
    "goals": [],
    "bookings": [],
    "subs": [],
    "shootout": []
  },
  {
    "id": "M-2026-62",
    "slug": "uzbekistan-vs-colombia",
    "status": "finished",
    "date": "2026-06-18",
    "time": "",
    "kickoffUtc": "2026-06-18T02:00:00Z",
    "venueId": "azteca",
    "stadium": "Estadio Azteca",
    "city": "Mexico City",
    "country": "Mexico",
    "group": "Group K",
    "stage": "group stage",
    "groupStage": true,
    "home": {
      "id": "T-UZB",
      "name": "Uzbekistan",
      "code": "UZB",
      "nameKo": "우즈베키스탄"
    },
    "away": {
      "id": "T-COL",
      "name": "Colombia",
      "code": "COL",
      "nameKo": "콜롬비아"
    },
    "homeScore": 1,
    "awayScore": 3,
    "penaltyShootout": false,
    "homePenalties": 0,
    "awayPenalties": 0,
    "result": "loss",
    "lineups": {
      "home": [],
      "away": []
    },
    "goals": [],
    "bookings": [],
    "subs": [],
    "shootout": []
  },
  {
    "id": "M-2026-63",
    "slug": "portugal-vs-uzbekistan",
    "status": "scheduled",
    "date": "2026-06-24",
    "time": "",
    "kickoffUtc": "2026-06-23T17:00:00Z",
    "venueId": "houston",
    "stadium": "NRG Stadium",
    "city": "Houston",
    "country": "United States",
    "group": "Group K",
    "stage": "group stage",
    "groupStage": true,
    "home": {
      "id": "T-POR",
      "name": "Portugal",
      "code": "POR",
      "nameKo": "포르투갈"
    },
    "away": {
      "id": "T-UZB",
      "name": "Uzbekistan",
      "code": "UZB",
      "nameKo": "우즈베키스탄"
    },
    "homeScore": 0,
    "awayScore": 0,
    "penaltyShootout": false,
    "homePenalties": 0,
    "awayPenalties": 0,
    "result": "draw",
    "lineups": {
      "home": [],
      "away": []
    },
    "goals": [],
    "bookings": [],
    "subs": [],
    "shootout": []
  },
  {
    "id": "M-2026-64",
    "slug": "colombia-vs-dr-congo",
    "status": "scheduled",
    "date": "2026-06-24",
    "time": "",
    "kickoffUtc": "2026-06-24T02:00:00Z",
    "venueId": "akron",
    "stadium": "Estadio Akron",
    "city": "Zapopan",
    "country": "Mexico",
    "group": "Group K",
    "stage": "group stage",
    "groupStage": true,
    "home": {
      "id": "T-COL",
      "name": "Colombia",
      "code": "COL",
      "nameKo": "콜롬비아"
    },
    "away": {
      "id": "T-COD",
      "name": "DR Congo",
      "code": "COD",
      "nameKo": "콩고민주공화국"
    },
    "homeScore": 0,
    "awayScore": 0,
    "penaltyShootout": false,
    "homePenalties": 0,
    "awayPenalties": 0,
    "result": "draw",
    "lineups": {
      "home": [],
      "away": []
    },
    "goals": [],
    "bookings": [],
    "subs": [],
    "shootout": []
  },
  {
    "id": "M-2026-65",
    "slug": "colombia-vs-portugal",
    "status": "scheduled",
    "date": "2026-06-28",
    "time": "",
    "kickoffUtc": "2026-06-27T23:30:00Z",
    "venueId": "miami",
    "stadium": "Hard Rock Stadium",
    "city": "Miami Gardens",
    "country": "United States",
    "group": "Group K",
    "stage": "group stage",
    "groupStage": true,
    "home": {
      "id": "T-COL",
      "name": "Colombia",
      "code": "COL",
      "nameKo": "콜롬비아"
    },
    "away": {
      "id": "T-POR",
      "name": "Portugal",
      "code": "POR",
      "nameKo": "포르투갈"
    },
    "homeScore": 0,
    "awayScore": 0,
    "penaltyShootout": false,
    "homePenalties": 0,
    "awayPenalties": 0,
    "result": "draw",
    "lineups": {
      "home": [],
      "away": []
    },
    "goals": [],
    "bookings": [],
    "subs": [],
    "shootout": []
  },
  {
    "id": "M-2026-66",
    "slug": "dr-congo-vs-uzbekistan",
    "status": "scheduled",
    "date": "2026-06-28",
    "time": "",
    "kickoffUtc": "2026-06-27T23:30:00Z",
    "venueId": "atlanta",
    "stadium": "Mercedes-Benz Stadium",
    "city": "Atlanta",
    "country": "United States",
    "group": "Group K",
    "stage": "group stage",
    "groupStage": true,
    "home": {
      "id": "T-COD",
      "name": "DR Congo",
      "code": "COD",
      "nameKo": "콩고민주공화국"
    },
    "away": {
      "id": "T-UZB",
      "name": "Uzbekistan",
      "code": "UZB",
      "nameKo": "우즈베키스탄"
    },
    "homeScore": 0,
    "awayScore": 0,
    "penaltyShootout": false,
    "homePenalties": 0,
    "awayPenalties": 0,
    "result": "draw",
    "lineups": {
      "home": [],
      "away": []
    },
    "goals": [],
    "bookings": [],
    "subs": [],
    "shootout": []
  },
  {
    "id": "M-2026-67",
    "slug": "england-vs-croatia",
    "status": "finished",
    "date": "2026-06-18",
    "time": "",
    "kickoffUtc": "2026-06-17T20:00:00Z",
    "venueId": "arlington",
    "stadium": "AT&T Stadium",
    "city": "Arlington",
    "country": "United States",
    "group": "Group L",
    "stage": "group stage",
    "groupStage": true,
    "home": {
      "id": "T-ENG",
      "name": "England",
      "code": "ENG",
      "nameKo": "잉글랜드"
    },
    "away": {
      "id": "T-CRO",
      "name": "Croatia",
      "code": "CRO",
      "nameKo": "크로아티아"
    },
    "homeScore": 4,
    "awayScore": 2,
    "penaltyShootout": false,
    "homePenalties": 0,
    "awayPenalties": 0,
    "result": "win",
    "lineups": {
      "home": [],
      "away": []
    },
    "goals": [],
    "bookings": [],
    "subs": [],
    "shootout": []
  },
  {
    "id": "M-2026-68",
    "slug": "ghana-vs-panama",
    "status": "finished",
    "date": "2026-06-18",
    "time": "",
    "kickoffUtc": "2026-06-17T23:00:00Z",
    "venueId": "toronto",
    "stadium": "BMO Field",
    "city": "Toronto",
    "country": "Canada",
    "group": "Group L",
    "stage": "group stage",
    "groupStage": true,
    "home": {
      "id": "T-GHA",
      "name": "Ghana",
      "code": "GHA",
      "nameKo": "가나"
    },
    "away": {
      "id": "T-PAN",
      "name": "Panama",
      "code": "PAN",
      "nameKo": "파나마"
    },
    "homeScore": 1,
    "awayScore": 0,
    "penaltyShootout": false,
    "homePenalties": 0,
    "awayPenalties": 0,
    "result": "win",
    "lineups": {
      "home": [],
      "away": []
    },
    "goals": [],
    "bookings": [],
    "subs": [],
    "shootout": []
  },
  {
    "id": "M-2026-69",
    "slug": "england-vs-ghana",
    "status": "scheduled",
    "date": "2026-06-24",
    "time": "",
    "kickoffUtc": "2026-06-23T20:00:00Z",
    "venueId": "foxborough",
    "stadium": "Gillette Stadium",
    "city": "Foxborough",
    "country": "United States",
    "group": "Group L",
    "stage": "group stage",
    "groupStage": true,
    "home": {
      "id": "T-ENG",
      "name": "England",
      "code": "ENG",
      "nameKo": "잉글랜드"
    },
    "away": {
      "id": "T-GHA",
      "name": "Ghana",
      "code": "GHA",
      "nameKo": "가나"
    },
    "homeScore": 0,
    "awayScore": 0,
    "penaltyShootout": false,
    "homePenalties": 0,
    "awayPenalties": 0,
    "result": "draw",
    "lineups": {
      "home": [],
      "away": []
    },
    "goals": [],
    "bookings": [],
    "subs": [],
    "shootout": []
  },
  {
    "id": "M-2026-70",
    "slug": "panama-vs-croatia",
    "status": "scheduled",
    "date": "2026-06-24",
    "time": "",
    "kickoffUtc": "2026-06-23T23:00:00Z",
    "venueId": "toronto",
    "stadium": "BMO Field",
    "city": "Toronto",
    "country": "Canada",
    "group": "Group L",
    "stage": "group stage",
    "groupStage": true,
    "home": {
      "id": "T-PAN",
      "name": "Panama",
      "code": "PAN",
      "nameKo": "파나마"
    },
    "away": {
      "id": "T-CRO",
      "name": "Croatia",
      "code": "CRO",
      "nameKo": "크로아티아"
    },
    "homeScore": 0,
    "awayScore": 0,
    "penaltyShootout": false,
    "homePenalties": 0,
    "awayPenalties": 0,
    "result": "draw",
    "lineups": {
      "home": [],
      "away": []
    },
    "goals": [],
    "bookings": [],
    "subs": [],
    "shootout": []
  },
  {
    "id": "M-2026-71",
    "slug": "panama-vs-england",
    "status": "scheduled",
    "date": "2026-06-28",
    "time": "",
    "kickoffUtc": "2026-06-27T21:00:00Z",
    "venueId": "eastrutherford",
    "stadium": "MetLife Stadium",
    "city": "East Rutherford",
    "country": "United States",
    "group": "Group L",
    "stage": "group stage",
    "groupStage": true,
    "home": {
      "id": "T-PAN",
      "name": "Panama",
      "code": "PAN",
      "nameKo": "파나마"
    },
    "away": {
      "id": "T-ENG",
      "name": "England",
      "code": "ENG",
      "nameKo": "잉글랜드"
    },
    "homeScore": 0,
    "awayScore": 0,
    "penaltyShootout": false,
    "homePenalties": 0,
    "awayPenalties": 0,
    "result": "draw",
    "lineups": {
      "home": [],
      "away": []
    },
    "goals": [],
    "bookings": [],
    "subs": [],
    "shootout": []
  },
  {
    "id": "M-2026-72",
    "slug": "croatia-vs-ghana",
    "status": "scheduled",
    "date": "2026-06-28",
    "time": "",
    "kickoffUtc": "2026-06-27T21:00:00Z",
    "venueId": "philadelphia",
    "stadium": "Lincoln Financial Field",
    "city": "Philadelphia",
    "country": "United States",
    "group": "Group L",
    "stage": "group stage",
    "groupStage": true,
    "home": {
      "id": "T-CRO",
      "name": "Croatia",
      "code": "CRO",
      "nameKo": "크로아티아"
    },
    "away": {
      "id": "T-GHA",
      "name": "Ghana",
      "code": "GHA",
      "nameKo": "가나"
    },
    "homeScore": 0,
    "awayScore": 0,
    "penaltyShootout": false,
    "homePenalties": 0,
    "awayPenalties": 0,
    "result": "draw",
    "lineups": {
      "home": [],
      "away": []
    },
    "goals": [],
    "bookings": [],
    "subs": [],
    "shootout": []
  }
]